{
    "Northern Africa": [
        "Algeria",
        "Egypt",
        "Libya",
        "Morocco",
        "Sudan",
        "Tunisia",
        "Western Sahara",
        "Niger",
        "Chad",
        "Mali",
        "Mauritania",
        "Eritrea",
        "Senegal",
        "Gambia"
    ],
    "Central West Africa": [
        "Benin",
        "Burkina Faso",
        "Cabo Verde",
        "Cameroon",
        "Central African Republic",
        "Congo",
        "Côte d'Ivoire",
        "Democratic Republic of the Congo",
        "Equatorial Guinea",
        "Gabon",
        "Ghana",
        "Guinea",
        "Guinea-Bissau",
        "Liberia",
        "Mauritius",
        "Nigeria",
        "Sao Tome and Principe",
        "Sierra Leone",
        "Togo"
    ],
    "Central East Africa:": [
        "South Sudan",
        "Rwanda",
        "Uganda",
        "Kenya",
        "Ethiopia",
        "Djibouti",
        "Tanzania, United Republic of",
        "Somalia",
        "Seychelles",
        "Comoros",
        "Burundi"
    ],
    "Southern Africa": [
        "Angola",
        "Botswana",
        "Namibia",
        "Zambia",
        "Zimbabwe",
        "South Africa",
        "Mozambique",
        "Madagascar",
        "Malawi",
        "Mayotte",
        "Réunion",
        "Lesotho",
        "Eswatini"
    ],
    "Middle East": [
        "Armenia",
        "Azerbaijan",
        "Bahrain",
        "Cyprus",
        "Georgia",
        "Iraq",
        "Israel",
        "Jordan",
        "Kuwait",
        "Lebanon",
        "Oman",
        "Palestine",
        "Qatar",
        "Saudi Arabia",
        "Syria",
        "Turkey",
        "United Arab Emirates",
        "Yemen"
    ],
    "Central Asia": [
        "Kazakhstan",
        "Kyrgyzstan",
        "Tajikistan",
        "Turkmenistan",
        "Uzbekistan"
    ],
    "Eastern Asia": [
        "China",
        "Hong Kong",
        "Japan",
        "Macau",
        "Mongolia",
        "North Korea",
        "South Korea",
        "Taiwan"
    ],
    "Southern Asia": [
        "Afghanistan",
        "Bangladesh",
        "Bhutan",
        "India",
        "Iran",
        "Maldives",
        "Nepal",
        "Pakistan",
        "Sri Lanka"
    ],
    "South Eastern Asia": [
        "Brunei Darussalam",
        "Cambodia",
        "Indonesia",
        "Laos",
        "Malaysia",
        "Myanmar",
        "Philippines",
        "Singapore",
        "Thailand",
        "Timor-Leste",
        "Viet Nam",
        "Guam"
    ],
    "Oceania": [
        "Australia",
        "Fiji",
        "Kiribati",
        "Marshall Islands",
        "Micronesia",
        "Nauru",
        "New Zealand",
        "Palau",
        "Papua New Guinea",
        "Samoa",
        "Solomon Islands",
        "Tonga",
        "Tuvalu",
        "Vanuatu"
    ],
    "Western Europe": [
        "Austria",
        "Belgium",
        "France",
        "Germany",
        "Liechtenstein",
        "Luxembourg",
        "Monaco",
        "Netherlands",
        "Switzerland"
    ],
    "Eastern Europe": [
        "Belarus",
        "Bulgaria",
        "Czech Republic",
        "Hungary",
        "Moldova",
        "Poland",
        "Romania",
        "Russian Federation",
        "Slovakia",
        "Ukraine",
        "Kosovo"
    ],
    "Northern Europe": [
        "Denmark",
        "Estonia",
        "Finland",
        "Iceland",
        "Ireland",
        "Latvia",
        "Lithuania",
        "Norway",
        "Sweden",
        "United Kingdom",
        "Faroe Islands",
        "Greenland"
    ],
    "Southern Europe": [
        "Albania",
        "Andorra",
        "Bosnia and Herzegovina",
        "Croatia",
        "Greece",
        "Holy See (Vatican City State)",
        "Italy",
        "Malta",
        "Montenegro",
        "North Macedonia",
        "Portugal",
        "San Marino",
        "Serbia",
        "Slovenia",
        "Spain",
        "Gibraltar",
        "Jersey",
        "Guernsey"
    ],
    "North America": ["United States", "Canada"],
    "South America": [
        "Argentina",
        "Bolivia, Plurinational State of",
        "Brazil",
        "Chile",
        "Colombia",
        "Ecuador",
        "Guyana",
        "Paraguay",
        "Peru",
        "Suriname",
        "Uruguay",
        "Venezuela",
        "French Guiana"
    ],
    "Central America": [
        "Belize",
        "Costa Rica",
        "El Salvador",
        "Guatemala",
        "Honduras",
        "Mexico",
        "Nicaragua",
        "Panama"
    ],
    "Caribbean": [
        "Aruba",
        "Antigua and Barbuda",
        "Bahamas",
        "Barbados",
        "Cayman Islands",
        "Curaçao",
        "Cuba",
        "Dominica",
        "Dominican Republic",
        "Grenada",
        "Haiti",
        "Jamaica",
        "Saint Kitts and Nevis",
        "Saint Lucia",
        "Saint Vincent and the Grenadines",
        "Trinidad and Tobago",
        "Guadeloupe",
        "Puerto Rico",
        "Saint Barthélemy",
        "Martinique",
        "Saint Martin"
    ]
}